msrc/appconfig/__init__.py
msrc/appconfig/decl.py
msrc/appconfig/logger.py
msrc/appconfig/py.typed
msrc/appconfig/read_all.py
msrc/appconfig/read_argv.py
msrc/appconfig/read_environ.py
msrc/appconfig/read_files.py
msrc/appconfig/read_mapping.py
msrc/appconfig/schema.py
msrc/appconfig_decl/decl_namedtuples.py
msrc/appconfig_decl/py.typed
msrc_appconfig-0.5.8.dist-info/METADATA
msrc_appconfig-0.5.8.dist-info/WHEEL
msrc_appconfig-0.5.8.dist-info/top_level.txt
msrc_appconfig-0.5.8.dist-info/RECORD
