Metadata-Version: 2.4
Name: msrc-appconfig
Version: 0.5.8
Summary: Orchestrates application configuration from config files, shell variables and command line arguments.
Home-page: https://github.com/microsoft/msrc-appconfig
Author: Vassily Lyutsarev
Author-email: vassilyl@microsoft.com
License: MIT License
Classifier: Programming Language :: Python :: 3
Classifier: License :: OSI Approved :: MIT License
Classifier: Operating System :: OS Independent
Requires-Python: >=3.7
Requires-Dist: ruamel.yaml
Requires-Dist: typing_extensions
Provides-Extra: attrs
Requires-Dist: msrc-appconfig-attrs==0.5.8; extra == "attrs"
Provides-Extra: dataclasses
Requires-Dist: msrc-appconfig-dataclasses==0.5.8; extra == "dataclasses"
Provides-Extra: param
Requires-Dist: msrc-appconfig-param==0.5.8; extra == "param"
Dynamic: author
Dynamic: author-email
Dynamic: classifier
Dynamic: description
Dynamic: description-content-type
Dynamic: home-page
Dynamic: license
Dynamic: provides-extra
Dynamic: requires-dist
Dynamic: requires-python
Dynamic: summary
